apiverve_coordinatesaresea/__init__.py
apiverve_coordinatesaresea/apiClient.py
apiverve_coordinatesaresea/exceptions.py
apiverve_coordinatesaresea/setup.py
apiverve_coordinatesaresea/setup_dep.py
apiverve_coordinatesaresea/tests/__init__.py
apiverve_coordinatesaresea/tests/test_api.py
apiverve_coordinatesaresea-1.1.7.dist-info/LICENSE
apiverve_coordinatesaresea-1.1.7.dist-info/METADATA
apiverve_coordinatesaresea-1.1.7.dist-info/WHEEL
apiverve_coordinatesaresea-1.1.7.dist-info/top_level.txt
apiverve_coordinatesaresea-1.1.7.dist-info/RECORD
